swift_scality_backend/__init__.py
swift_scality_backend/cli.py
swift_scality_backend/diskfile.py
swift_scality_backend/http_utils.py
swift_scality_backend/policy_configuration.py
swift_scality_backend/server.py
swift_scality_backend/splice_utils.py
swift_scality_backend/utils.py
swift_scality_backend-0.4.4.dist-info/AUTHORS
swift_scality_backend-0.4.4.dist-info/LICENSE
swift_scality_backend-0.4.4.dist-info/METADATA
swift_scality_backend-0.4.4.dist-info/WHEEL
swift_scality_backend-0.4.4.dist-info/entry_points.txt
swift_scality_backend-0.4.4.dist-info/top_level.txt
swift_scality_backend-0.4.4.dist-info/RECORD
