Metadata-Version: 2.1
Name: swift-scality-backend
Version: 0.4.4
Summary: Scality Ring backend for OpenStack Swift
Home-page: http://www.scality.com/
Author: Scality Openstack Engineering Team
Author-email: openstack-eng@scality.com
License: Apache License (2.0)
Platform: UNKNOWN
Classifier: License :: OSI Approved :: Apache Software License
Classifier: Operating System :: POSIX :: Linux
Classifier: Programming Language :: Python :: 2.7
Requires-Dist: swift (>=1.13.1)
Requires-Dist: eventlet (>=0.9.15)
Requires-Dist: scality-sproxyd-client (>=0.1.3)
